airflow/providers/snowflake/__init__.py
airflow/providers/snowflake/get_provider_info.py
airflow/providers/snowflake/version_compat.py
airflow/providers/snowflake/decorators/__init__.py
airflow/providers/snowflake/decorators/snowpark.py
airflow/providers/snowflake/hooks/__init__.py
airflow/providers/snowflake/hooks/snowflake.py
airflow/providers/snowflake/hooks/snowflake_sql_api.py
airflow/providers/snowflake/operators/__init__.py
airflow/providers/snowflake/operators/snowflake.py
airflow/providers/snowflake/operators/snowpark.py
airflow/providers/snowflake/transfers/__init__.py
airflow/providers/snowflake/transfers/copy_into_snowflake.py
airflow/providers/snowflake/triggers/__init__.py
airflow/providers/snowflake/triggers/snowflake_trigger.py
airflow/providers/snowflake/utils/__init__.py
airflow/providers/snowflake/utils/common.py
airflow/providers/snowflake/utils/openlineage.py
airflow/providers/snowflake/utils/snowpark.py
airflow/providers/snowflake/utils/sql_api_generate_jwt.py
apache_airflow_providers_snowflake-6.8.2.dist-info/entry_points.txt
apache_airflow_providers_snowflake-6.8.2.dist-info/licenses/LICENSE
apache_airflow_providers_snowflake-6.8.2.dist-info/licenses/NOTICE
apache_airflow_providers_snowflake-6.8.2.dist-info/WHEEL
apache_airflow_providers_snowflake-6.8.2.dist-info/METADATA
apache_airflow_providers_snowflake-6.8.2.dist-info/RECORD
