Metadata-Version: 2.4
Name: apache-airflow-providers-snowflake
Version: 6.8.2
Summary: Provider package apache-airflow-providers-snowflake for Apache Airflow
Keywords: airflow-provider,snowflake,airflow,integration
Author-email: Apache Software Foundation <dev@airflow.apache.org>
Maintainer-email: Apache Software Foundation <dev@airflow.apache.org>
Requires-Python: >=3.10
License-Expression: Apache-2.0
Classifier: Development Status :: 5 - Production/Stable
Classifier: Environment :: Console
Classifier: Environment :: Web Environment
Classifier: Intended Audience :: Developers
Classifier: Intended Audience :: System Administrators
Classifier: Framework :: Apache Airflow
Classifier: Framework :: Apache Airflow :: Provider
Classifier: Programming Language :: Python :: 3.10
Classifier: Programming Language :: Python :: 3.11
Classifier: Programming Language :: Python :: 3.12
Classifier: Programming Language :: Python :: 3.13
Classifier: Topic :: System :: Monitoring
License-File: LICENSE
License-File: NOTICE
Requires-Dist: apache-airflow>=2.11.0
Requires-Dist: apache-airflow-providers-common-compat>=1.12.0
Requires-Dist: apache-airflow-providers-common-sql>=1.27.5
Requires-Dist: pandas>=2.1.2; python_version <"3.13"
Requires-Dist: pandas>=2.2.3; python_version >="3.13"
Requires-Dist: pyarrow>=16.1.0; python_version < '3.13'
Requires-Dist: pyarrow>=18.0.0; python_version >= '3.13'
Requires-Dist: snowflake-connector-python>=3.16.0
Requires-Dist: snowflake-sqlalchemy>=1.7.0
Requires-Dist: snowflake-snowpark-python>=1.17.0,<9999;python_version<'3.12'
Requires-Dist: snowflake-snowpark-python>=1.27.0,<9999;python_version>='3.12' and python_version<'3.14'
Requires-Dist: setuptools>=80.0.0,<9999
Requires-Dist: apache-airflow-providers-microsoft-azure>=12.8.0 ; extra == "microsoft-azure"
Requires-Dist: apache-airflow-providers-openlineage>=2.3.0 ; extra == "openlineage"
Project-URL: Bug Tracker, https://github.com/apache/airflow/issues
Project-URL: Changelog, https://airflow.apache.org/docs/apache-airflow-providers-snowflake/6.8.2/changelog.html
Project-URL: Documentation, https://airflow.apache.org/docs/apache-airflow-providers-snowflake/6.8.2
Project-URL: Mastodon, https://fosstodon.org/@airflow
Project-URL: Slack Chat, https://s.apache.org/airflow-slack
Project-URL: Source Code, https://github.com/apache/airflow
Project-URL: YouTube, https://www.youtube.com/channel/UCSXwxpWZQ7XZ1WL3wqevChA/
Provides-Extra: microsoft-azure
Provides-Extra: openlineage
